{
    "stage": "dev",
    "scale": true,
    "shorter_lookback_for_finetuning": 104,
    "shorter_future_for_finetuning": 4,
    "force_legacy_lookback_for_inference": 104, 
    "force_training_set_split_rate": 0.729,
    "number_of_targets": 53,
    "max_L_I": 4096,
    "lookback": 768,
    "future": 768,
    "randomized_training_flag": true,
    "random_series_shuffle": false,
    "force_resize_time_series_to_size_limit": false,
    "zero_padding_to_hard_token_limit": true,
    "soft_token_limit": 2048,
    "hard_token_limit": 2048,
    "sampling_step": 2,
    "max_channel_vocab_size": 4096,
    "max_position_vocab_size": 4096,
    "max_source_vocab_size": 4096,
    "max_tag_vocab_size": 4096,
    "number_of_targets": 0,
    "n_series_registrar": 0,
    "cls_max_random_number_of_targets": 8,
    "root_path": "dataset_finetune",
    "training_soft_series_limit": 1024,
    "db_path": "data_sources_finetune.db",
    "current_ds_type": "both",
    "source_weight_cls": {
        "ETTh2": 0
    },
    "token_type_weight_cls": {
        "forecasting": 0,
        "classification": 1,
        "imitation": 0,
        "imputation": 0,
        "cropping": 0,
        "reflection": 0,
        "shifting": 0,
        "hyperres": 0,
        "statistics": 0,
        "differencing": 0,
        "movingavg": 0,
        "expsmoothing": 0,
        "decomposition": 0
    },
    "source_weight_reg": {
        "ETTh2": 1
    },
    "token_type_weight_reg": {
        "forecasting": 1,
        "classification": 0,
        "imitation": 0,
        "imputation": 0.0,
        "cropping": 0.0,
        "reflection": 0.0,
        "shifting": 0.0,
        "hyperres": 0.0,
        "statistics": 0,
        "differencing": 0.0,
        "movingavg": 0.0,
        "expsmoothing": 0,
        "decomposition": 0
    },
    "ds_len": 4000,
    "batch_size": 8,
    "num_workers": 12,
    "rebuild_every": 96000,
    "d_model": 768,
    "n_layers": 12,
    "n_heads": 12,
    "mlp_ratio": 4,
    "dropout": 0.0,
    "enable_task_embedding": true,
    "use_legacy_dataloader": true,
    "tokenization_mode": "sequential",
    "compile": true
}